LICENSE
MANIFEST.in
README
README.md
flask_swagger.py
setup.py
flask_swagger.egg-info/PKG-INFO
flask_swagger.egg-info/SOURCES.txt
flask_swagger.egg-info/dependency_links.txt
flask_swagger.egg-info/requires.txt
flask_swagger.egg-info/top_level.txt