Metadata-Version: 1.0
Name: flask-swagger
Version: 0.2.0
Summary: Extract swagger specs from your flast-restful project
Home-page: https://github.com/gangverk/flask-swagger
Author: Atli Thorbjornsson
Author-email: UNKNOWN
License: MIT
Platform: UNKNOWN
